.gitignore
CHANGES.txt
LICENSE.txt
MANIFEST.in
README.rst
README.txt
TODO.rst
initcred.py
setup.cfg
setup.py
tox.ini
PyGSSAPI.egg-info/PKG-INFO
PyGSSAPI.egg-info/SOURCES.txt
PyGSSAPI.egg-info/dependency_links.txt
PyGSSAPI.egg-info/requires.txt
PyGSSAPI.egg-info/top_level.txt
docs/Makefile
docs/make.bat
docs/build/doctrees/environment.pickle
docs/build/doctrees/gssapi.base.doctree
docs/build/doctrees/gssapi.doctree
docs/build/doctrees/index.doctree
docs/build/html/.buildinfo
docs/build/html/genindex.html
docs/build/html/gssapi.base.html
docs/build/html/gssapi.html
docs/build/html/index.html
docs/build/html/objects.inv
docs/build/html/py-modindex.html
docs/build/html/search.html
docs/build/html/searchindex.js
docs/build/html/_modules/index.html
docs/build/html/_modules/gssapi/client.html
docs/build/html/_modules/gssapi/type_wrappers.html
docs/build/html/_modules/gssapi/base/impl.html
docs/build/html/_modules/gssapi/base/status_utils.html
docs/build/html/_modules/gssapi/base/types.html
docs/build/html/_sources/gssapi.base.txt
docs/build/html/_sources/gssapi.txt
docs/build/html/_sources/index.txt
docs/build/html/_static/ajax-loader.gif
docs/build/html/_static/basic.css
docs/build/html/_static/comment-bright.png
docs/build/html/_static/comment-close.png
docs/build/html/_static/comment.png
docs/build/html/_static/default.css
docs/build/html/_static/doctools.js
docs/build/html/_static/down-pressed.png
docs/build/html/_static/down.png
docs/build/html/_static/file.png
docs/build/html/_static/jquery.js
docs/build/html/_static/minus.png
docs/build/html/_static/plus.png
docs/build/html/_static/pygments.css
docs/build/html/_static/searchtools.js
docs/build/html/_static/sidebar.js
docs/build/html/_static/underscore.js
docs/build/html/_static/up-pressed.png
docs/build/html/_static/up.png
docs/build/html/_static/websupport.js
docs/source/conf.py
docs/source/gssapi.base.rst
docs/source/gssapi.rst
docs/source/index.rst
gssapi/__init__.py
gssapi/client.py
gssapi/type_wrappers.py
gssapi/base/__init__.py
gssapi/base/ctypes.py
gssapi/base/impl.py
gssapi/base/status_utils.py
gssapi/base/types.py
gssapi/tests/__init__.py
