Metadata-Version: 1.1
Name: PyGSSAPI
Version: 1.0.0
Summary: Python GSSAPI Wrapper
Home-page: https://github.com/directxman12/python-gssapi
Author: Solly Ross
Author-email: sross@redhat.com
License: LICENSE.txt
Platform: UNKNOWN
Classifier: Development Status :: 4 - Beta
Classifier: Programming Language :: Python
Classifier: Programming Language :: Python :: 2.6
Classifier: Programming Language :: Python :: 2.7
Classifier: Programming Language :: Python :: 3
Classifier: Intended Audience :: Developers
Classifier: License :: OSI Approved :: BSD License
Classifier: Programming Language :: Python :: Implementation :: CPython
Classifier: Topic :: Security
Classifier: Topic :: Software Development :: Libraries :: Python Modules
